visarchpy/__init__.py
visarchpy/analytics.py
visarchpy/captions.py
visarchpy/default-settings.json
visarchpy/metadata.py
visarchpy/ocr.py
visarchpy/pdf.py
visarchpy/pipelines.py
visarchpy/utils.py
visarchpy/cli/dino.py
visarchpy/cli/layout.py
visarchpy/cli/layout_ocr.py
visarchpy/cli/main.py
visarchpy/cli/ocr.py
visarchpy/cli/settings.py
visarchpy/cli/viz.py
visarchpy/dino/__init__.py
visarchpy/dino/transformer.py
visarchpy/models/__init__.py
visarchpy-1.0.4.dist-info/LICENSE
visarchpy-1.0.4.dist-info/METADATA
visarchpy-1.0.4.dist-info/WHEEL
visarchpy-1.0.4.dist-info/entry_points.txt
visarchpy-1.0.4.dist-info/top_level.txt
visarchpy-1.0.4.dist-info/RECORD
