Metadata-Version: 2.1
Name: visarchpy
Version: 1.0.4
Summary: Data pipelines for extraction, transformation and visualization of architectural visuals in Python.
Author-email: Manuel Garcia <m.g.garciaalvarez@tudelft.nl>
License: MIT
Project-URL: Documentation, https://visarchpy.readthedocs.io
Project-URL: Repository, https://github.com/AiDAPT-A/VisArchPy.git
Project-URL: Bug Tracker, https://github.com/AiDAPT-A/VisArchPy/issues
Keywords: data pipelines,visuals,architecture,pdf,ETL,computer vision,dino,TU Delft
Classifier: Development Status :: 5 - Production/Stable
Classifier: Intended Audience :: Science/Research
Classifier: Operating System :: OS Independent
Classifier: Programming Language :: Python :: 3.10
Classifier: Programming Language :: Python :: 3.11
Classifier: Environment :: Console
Classifier: Framework :: Pytest
Classifier: License :: OSI Approved :: MIT License
Classifier: Intended Audience :: Science/Research
Classifier: Topic :: Utilities
Requires-Python: >=3.10
License-File: LICENSE
Requires-Dist: Pillow
Requires-Dist: requests
Requires-Dist: pdfminer.six[image]
Requires-Dist: beautifulsoup4
Requires-Dist: shapely
Requires-Dist: pandas
Requires-Dist: pymods
Requires-Dist: tqdm
Requires-Dist: pdf2image
Requires-Dist: pytesseract
Requires-Dist: matplotlib
Requires-Dist: typer
Requires-Dist: transformers
Requires-Dist: scikit-learn
Provides-Extra: dev
Requires-Dist: pytest ; extra == 'dev'
Requires-Dist: Sphinx ; extra == 'dev'
Requires-Dist: sphinx-rtd-theme ; extra == 'dev'
Requires-Dist: sphinx-copybutton ==0.5.2 ; extra == 'dev'
Requires-Dist: sphinx-tabs ==3.4.4 ; extra == 'dev'
